mcp_plus/__init__.py
mcp_plus/__main__.py
mcp_plus-0.1.0.dist-info/METADATA
mcp_plus-0.1.0.dist-info/WHEEL
mcp_plus-0.1.0.dist-info/RECORD
