Metadata-Version: 2.4
Name: mcp-plus
Version: 0.1.0
Summary: MCP Plus - 品牌广告封面生成工具，支持多种风格和自定义配置
Project-URL: Homepage, https://github.com/shidianxiaoerya/mcp-plus
Project-URL: Repository, https://github.com/shidianxiaoerya/mcp-plus
Project-URL: Issues, https://github.com/shidianxiaoerya/mcp-plus/issues
Author-email: shidianxiaoerya <934679045@qq.com>
License: MIT
Keywords: brand,cover,generator,mcp,svg
Classifier: Development Status :: 4 - Beta
Classifier: Intended Audience :: Developers
Classifier: License :: OSI Approved :: MIT License
Classifier: Programming Language :: Python :: 3
Classifier: Programming Language :: Python :: 3.13
Requires-Python: >=3.13
Requires-Dist: mcp[cli]>=1.12.4
